Unidad 3 - Codigos de Control de Errores/unidad3_rtl/unidad3/hamming_7_4_decoder/error_corrector.sv
module error_corrector (
    output logic [4-1:0] o_info,
    output logic         o_is_corrected,
    input  logic         i_zero_syndrome,
    input  logic [3-1:0] i_syndrome,
    input  logic [7-1:0] i_message,
    input  logic         i_clk,
    input  logic         i_rst
);

/*
    | 1 0 1 1 1 0 0 |
H = | 1 1 1 0 0 1 0 |
    | 0 1 1 1 0 0 1 |

h0 = 110 -> 3'b011
h1 = 011 -> 3'b110
h2 = 111 -> 3'b111
h3 = 101 -> 3'b101
h4 = 100 -> 3'b001
h5 = 010 -> 3'b010
h6 = 001 -> 3'b100

r = v + e
v + e + e = v
r + e = v
*/

logic [3-1:0] error_position;
logic [7-1:0] estimated_error; // e
logic [7-1:0] corrected_message;
logic [4-1:0] info_d;
logic         is_corrected_d;

always_comb begin
    case (i_syndrome)
        3'b011:  error_position = 3'd0; //h0
        3'b110:  error_position = 3'd1; //h1
        3'b111:  error_position = 3'd2; //h2
        3'b101:  error_position = 3'd3; //h3
        3'b001:  error_position = 3'd4; //h4
        3'b010:  error_position = 3'd5; //h5
        3'b100:  error_position = 3'd6; //h6
        default: error_position = 3'd0;
    endcase
end

always_comb begin
    estimated_error                 = 7'd0;
    estimated_error[error_position] = 1'b1;
end

assign corrected_message = (i_zero_syndrome) ? i_message : (i_message ^ estimated_error);

always_ff @(posedge i_clk) begin
    if(i_rst) begin
        info_d         <= 4'd0;
        is_corrected_d <= 1'b0;
    end
    else begin
        info_d         <= corrected_message[3:0];
        is_corrected_d <= !i_zero_syndrome;
    end
end

assign o_info         = info_d;
assign o_is_corrected = is_corrected_d;

endmodule

Unidad 3 - Codigos de Control de Errores/unidad3_rtl/unidad3/hamming_7_4_decoder/syndrome_calculator.sv
module syndrome_calculator (
    output logic [3-1:0] o_syndrome,
    output logic         o_zero_syndrome,
    input  logic [7-1:0] i_message,
    input  logic         i_clk,
    input  logic         i_rst
);

/*
    | 1 0 1 1 1 0 0 |
H = | 1 1 1 0 0 1 0 |
    | 0 1 1 1 0 0 1 |

      | 1 1 0 |
      | 0 1 1 |
      | 1 1 1 |
H^T = | 1 0 1 |
      | 1 0 0 |
      | 0 1 0 |
      | 0 0 1 |

s (syndrome) = r (received message) * H^T (transposed H)
r = v + e

s0 = r0 + r2 + r3 + r4
s1 = r0 + r1 + r2 + r5
s2 = r1 + r2 + r3 + r6
*/

logic [7-1:0] message_d;
logic [3-1:0] syndrome;

always_ff @(posedge i_clk) begin
    if(i_rst) begin
        message_d <= 7'd0;
    end
    else begin
        message_d <= i_message;
    end
end

always_comb begin
    syndrome[0] = message_d[0] ^ message_d[2] ^ message_d[3] ^ message_d[4];
    syndrome[1] = message_d[0] ^ message_d[1] ^ message_d[2] ^ message_d[5];
    syndrome[2] = message_d[1] ^ message_d[2] ^ message_d[3] ^ message_d[6];
end

assign o_syndrome      = syndrome;
assign o_zero_syndrome = (|syndrome == 1'b0);

// |syndrome = syndrome[0] | syndrome[1] | syndrome[2]

endmodule

Unidad 3 - Codigos de Control de Errores/unidad3_rtl/unidad3/hamming_7_4_decoder/hamming_decoder.sv
module hamming_decoder (
    output logic [4-1:0] o_info,
    output logic         o_is_corrected,
    input  logic [7-1:0] i_message,
    input  logic         i_clk,
    input  logic         i_rst
);

logic [7-1:0] message_d;
logic [3-1:0] syndrome;
logic         zero_syndrome;

always_ff @(posedge i_clk) begin
    message_d <= i_message;
end

syndrome_calculator u_syndrome_calculator(
    .o_syndrome      (syndrome),
    .o_zero_syndrome (zero_syndrome),
    .i_message       (i_message),
    .i_clk           (i_clk),
    .i_rst           (i_rst)
);

error_corrector u_error_corrector(
    .o_info          (o_info),
    .o_is_corrected  (o_is_corrected),
    .i_zero_syndrome (zero_syndrome),
    .i_syndrome      (syndrome),
    .i_message       (message_d),
    .i_clk           (i_clk),
    .i_rst           (i_rst)
);
    
endmodule

Unidad 3 - Codigos de Control de Errores/unidad3_rtl/unidad3/hamming_7_4_decoder/hamming_decoder.vcd
$date
	Tue Aug 11 02:21:05 2026
$end
$version
	Icarus Verilog
$end
$timescale
	1ps
$end
$scope module hamming_decoder $end
$var wire 1 ! i_clk $end
$var wire 7 " i_message [6:0] $end
$var wire 1 # i_rst $end
$var wire 1 $ zero_syndrome $end
$var wire 3 % syndrome [2:0] $end
$var wire 1 & o_is_corrected $end
$var wire 4 ' o_info [3:0] $end
$var reg 7 ( message_d [6:0] $end
$scope module u_error_corrector $end
$var wire 1 ! i_clk $end
$var wire 7 ) i_message [6:0] $end
$var wire 1 # i_rst $end
$var wire 4 * o_info [3:0] $end
$var wire 1 & o_is_corrected $end
$var wire 1 $ i_zero_syndrome $end
$var wire 3 + i_syndrome [2:0] $end
$var wire 7 , corrected_message [6:0] $end
$var reg 3 - error_position [2:0] $end
$var reg 7 . estimated_error [6:0] $end
$var reg 4 / info_d [3:0] $end
$var reg 1 0 is_corrected_d $end
$upscope $end
$scope module u_syndrome_calculator $end
$var wire 1 ! i_clk $end
$var wire 7 1 i_message [6:0] $end
$var wire 1 # i_rst $end
$var wire 3 2 o_syndrome [2:0] $end
$var wire 1 $ o_zero_syndrome $end
$var reg 7 3 message_d [6:0] $end
$var reg 3 4 syndrome [2:0] $end
$upscope $end
$upscope $end
$enddefinitions $end
$comment Show the parameter values. $end
$dumpall
$end
#0
$dumpvars
b0 4
b0 3
b0 2
b0 1
00
b0 /
b1 .
b0 -
b0 ,
b0 +
b0 *
b0 )
b0 (
b0 '
0&
b0 %
1$
1#
b0 "
1!
$end
#5000
0!
#10000
0#
1!
#15000
0!
#20000
1!
#21000
b1 "
b1 1
#25000
0!
#30000
0$
b0 ,
b11 %
b11 +
b11 2
b11 4
b1 (
b1 )
b1 3
1!
#31000
b10 "
b10 1
#35000
0!
#40000
b10 .
b1 -
b0 ,
b110 %
b110 +
b110 2
b110 4
b10 3
1&
10
b10 (
b10 )
1!
#41000
b11 "
b11 1
#45000
0!
#50000
b1000 .
b1011 ,
b11 -
b101 %
b101 +
b101 2
b101 4
b11 (
b11 )
b11 3
1!
#51000
b100 "
b100 1
#55000
0!
#60000
b100 .
b10 -
b0 ,
b111 %
b111 +
b111 2
b111 4
b100 3
b1011 '
b1011 *
b1011 /
b100 (
b100 )
1!
#61000
b101 "
b101 1
#65000
0!
#70000
b1000000 .
b1000101 ,
b110 -
b100 %
b100 +
b100 2
b100 4
b101 (
b101 )
b0 '
b0 *
b0 /
b101 3
1!
#71000
b110 "
b110 1
#75000
0!
#80000
b10000 .
b100 -
b10110 ,
b1 %
b1 +
b1 2
b1 4
b110 3
b101 '
b101 *
b101 /
b110 (
b110 )
1!
#81000
b111 "
b111 1
#85000
0!
#90000
b100000 .
b100111 ,
b101 -
b10 %
b10 +
b10 2
b10 4
b111 (
b111 )
b110 '
b110 *
b110 /
b111 3
1!
#91000
b1000 "
b1000 1
#95000
0!
#100000
b1000 .
b11 -
b0 ,
b101 %
b101 +
b101 2
b101 4
b1000 3
b111 '
b111 *
b111 /
b1000 (
b1000 )
1!
#101000
b1001 "
b1001 1
#105000
0!
#110000
b10 .
b1011 ,
b1 -
b110 %
b110 +
b110 2
b110 4
b1001 (
b1001 )
b0 '
b0 *
b0 /
b1001 3
1!
#111000
b1010 "
b1010 1
#115000
0!
#120000
b1 .
b0 -
b1011 ,
b11 %
b11 +
b11 2
b11 4
b1010 3
b1011 '
b1011 *
b1011 /
b1010 (
b1010 )
1!
#121000
b1011 "
b1011 1
#125000
0!
#130000
1$
b0 %
b0 +
b0 2
b0 4
b1011 (
b1011 )
b1011 3
1!
#131000
b1100 "
b1100 1
#135000
0!
#140000
b100000 .
0$
b101 -
b10 %
b10 +
b10 2
b10 4
b101100 ,
b1100 3
0&
00
b1100 (
b1100 )
1!
#141000
b1101 "
b1101 1
#145000
0!
#150000
b10000 .
b11101 ,
b100 -
b1 %
b1 +
b1 2
b1 4
b1101 (
b1101 )
1&
10
b1100 '
b1100 *
b1100 /
b1101 3
1!
#151000
b1110 "
b1110 1
#155000
0!
#160000
b1000000 .
b110 -
b1001110 ,
b100 %
b100 +
b100 2
b100 4
b1110 3
b1101 '
b1101 *
b1101 /
b1110 (
b1110 )
1!
#161000
b1111 "
b1111 1
#165000
0!
#170000
b100 .
b1011 ,
b10 -
b111 %
b111 +
b111 2
b111 4
b1111 (
b1111 )
b1110 '
b1110 *
b1110 /
b1111 3
1!
#171000
b10000 "
b10000 1
#175000
0!
#180000
b10000 .
b100 -
b0 ,
b1 %
b1 +
b1 2
b1 4
b10000 3
b1011 '
b1011 *
b1011 /
b10000 (
b10000 )
1!
#181000
b10001 "
b10001 1
#185000
0!
#190000
b100000 .
b110001 ,
b101 -
b10 %
b10 +
b10 2
b10 4
b10001 (
b10001 )
b0 '
b0 *
b0 /
b10001 3
1!
#191000
b10010 "
b10010 1
#195000
0!
#200000
b100 .
b10 -
b10110 ,
b111 %
b111 +
b111 2
b111 4
b10010 3
b1 '
b1 *
b1 /
b10010 (
b10010 )
1!
#201000
b10011 "
b10011 1
#205000
0!
#210000
b1000000 .
b1010011 ,
b110 -
b100 %
b100 +
b100 2
b100 4
b10011 (
b10011 )
b110 '
b110 *
b110 /
b10011 3
1!
#211000
b10100 "
b10100 1
#215000
0!
#220000
b10 .
b1 -
b10110 ,
b110 %
b110 +
b110 2
b110 4
b10100 3
b11 '
b11 *
b11 /
b10100 (
b10100 )
1!
#221000
b10101 "
b10101 1
#225000
0!
#230000
b1000 .
b11101 ,
b11 -
b101 %
b101 +
b101 2
b101 4
b10101 (
b10101 )
b110 '
b110 *
b110 /
b10101 3
1!
#231000
b10110 "
b10110 1
#235000
0!
#240000
b1 .
1$
b0 -
b10110 ,
b0 %
b0 +
b0 2
b0 4
b10110 3
b1101 '
b1101 *
b1101 /
b10110 (
b10110 )
1!
#241000
b10111 "
b10111 1
#245000
0!
#250000
0$
b10110 ,
b11 %
b11 +
b11 2
b11 4
b10111 (
b10111 )
0&
00
b110 '
b110 *
b110 /
b10111 3
1!
#251000
b11000 "
b11000 1
#255000
0!
#260000
b1000000 .
b110 -
b1011000 ,
b100 %
b100 +
b100 2
b100 4
b11000 3
1&
10
b11000 (
b11000 )
1!
#261000
b11001 "
b11001 1
#265000
0!
#270000
b100 .
b11101 ,
b10 -
b111 %
b111 +
b111 2
b111 4
b11001 (
b11001 )
b1000 '
b1000 *
b1000 /
b11001 3
1!
#271000
b11010 "
b11010 1
#275000
0!
#280000
b100000 .
b101 -
b111010 ,
b10 %
b10 +
b10 2
b10 4
b11010 3
b1101 '
b1101 *
b1101 /
b11010 (
b11010 )
1!
#281000
b11011 "
b11011 1
#285000
0!
#290000
b10000 .
b1011 ,
b100 -
b1 %
b1 +
b1 2
b1 4
b11011 (
b11011 )
b1010 '
b1010 *
b1010 /
b11011 3
1!
#291000
b11100 "
b11100 1
#295000
0!
#300000
b1 .
b0 -
b11101 ,
b11 %
b11 +
b11 2
b11 4
b11100 3
b1011 '
b1011 *
b1011 /
b11100 (
b11100 )
1!
#301000
b11101 "
b11101 1
#305000
0!
#310000
1$
b0 %
b0 +
b0 2
b0 4
b11101 (
b11101 )
b1101 '
b1101 *
b1101 /
b11101 3
1!
#311000
b11110 "
b11110 1
#315000
0!
#320000
b1000 .
0$
b11 -
b101 %
b101 +
b101 2
b101 4
b10110 ,
b11110 3
0&
00
b11110 (
b11110 )
1!
#321000
b11111 "
b11111 1
#325000
0!
#330000
b10 .
b11101 ,
b1 -
b110 %
b110 +
b110 2
b110 4
b11111 (
b11111 )
1&
10
b110 '
b110 *
b110 /
b11111 3
1!
#331000
b100000 "
b100000 1
#335000
0!
#340000
b100000 .
b101 -
b0 ,
b10 %
b10 +
b10 2
b10 4
b100000 3
b1101 '
b1101 *
b1101 /
b100000 (
b100000 )
1!
#341000
b100001 "
b100001 1
#345000
0!
#350000
b10000 .
b110001 ,
b100 -
b1 %
b1 +
b1 2
b1 4
b100001 (
b100001 )
b0 '
b0 *
b0 /
b100001 3
1!
#351000
b100010 "
b100010 1
#355000
0!
#360000
b1000000 .
b110 -
b1100010 ,
b100 %
b100 +
b100 2
b100 4
b100010 3
b1 '
b1 *
b1 /
b100010 (
b100010 )
1!
#361000
b100011 "
b100011 1
#365000
0!
#370000
b100 .
b100111 ,
b10 -
b111 %
b111 +
b111 2
b111 4
b100011 (
b100011 )
b10 '
b10 *
b10 /
b100011 3
1!
#371000
b100100 "
b100100 1
#375000
0!
#380000
b1000 .
b11 -
b101100 ,
b101 %
b101 +
b101 2
b101 4
b100100 3
b111 '
b111 *
b111 /
b100100 (
b100100 )
1!
#381000
b100101 "
b100101 1
#385000
0!
#390000
b10 .
b100111 ,
b1 -
b110 %
b110 +
b110 2
b110 4
b100101 (
b100101 )
b1100 '
b1100 *
b1100 /
b100101 3
1!
#391000
b100110 "
b100110 1
#395000
0!
#400000
b1 .
b0 -
b100111 ,
b11 %
b11 +
b11 2
b11 4
b100110 3
b111 '
b111 *
b111 /
b100110 (
b100110 )
1!
#401000
b100111 "
b100111 1
#405000
0!
#410000
1$
b0 %
b0 +
b0 2
b0 4
b100111 (
b100111 )
b100111 3
1!
#411000
b101000 "
b101000 1
#415000
0!
#420000
b100 .
0$
b10 -
b111 %
b111 +
b111 2
b111 4
b101100 ,
b101000 3
0&
00
b101000 (
b101000 )
1!
#421000
b101001 "
b101001 1
#425000
0!
#430000
b1000000 .
b1101001 ,
b110 -
b100 %
b100 +
b100 2
b100 4
b101001 (
b101001 )
1&
10
b1100 '
b1100 *
b1100 /
b101001 3
1!
#431000
b101010 "
b101010 1
#435000
0!
#440000
b10000 .
b100 -
b111010 ,
b1 %
b1 +
b1 2
b1 4
b101010 3
b1001 '
b1001 *
b1001 /
b101010 (
b101010 )
1!
#441000
b101011 "
b101011 1
#445000
0!
#450000
b100000 .
b1011 ,
b101 -
b10 %
b10 +
b10 2
b10 4
b101011 (
b101011 )
b1010 '
b1010 *
b1010 /
b101011 3
1!
#451000
b101100 "
b101100 1
#455000
0!
#460000
b1 .
1$
b0 -
b101100 ,
b0 %
b0 +
b0 2
b0 4
b101100 3
b1011 '
b1011 *
b1011 /
b101100 (
b101100 )
1!
#461000
b101101 "
b101101 1
#465000
0!
#470000
0$
b101100 ,
b11 %
b11 +
b11 2
b11 4
b101101 (
b101101 )
0&
00
b1100 '
b1100 *
b1100 /
b101101 3
1!
#471000
b101110 "
b101110 1
#475000
0!
#480000
b10 .
b1 -
b101100 ,
b110 %
b110 +
b110 2
b110 4
b101110 3
1&
10
b101110 (
b101110 )
1!
#481000
b101111 "
b101111 1
#485000
0!
#490000
b1000 .
b100111 ,
b11 -
b101 %
b101 +
b101 2
b101 4
b101111 (
b101111 )
b101111 3
1!
#491000
b110000 "
b110000 1
#495000
0!
#500000
b1 .
b0 -
b110001 ,
b11 %
b11 +
b11 2
b11 4
b110000 3
b111 '
b111 *
b111 /
b110000 (
b110000 )
1!
#501000
b110001 "
b110001 1
#505000
0!
#510000
1$
b0 %
b0 +
b0 2
b0 4
b110001 (
b110001 )
b1 '
b1 *
b1 /
b110001 3
1!
#511000
b110010 "
b110010 1
#515000
0!
#520000
b1000 .
0$
b11 -
b101 %
b101 +
b101 2
b101 4
b111010 ,
b110010 3
0&
00
b110010 (
b110010 )
1!
#521000
b110011 "
b110011 1
#525000
0!
#530000
b10 .
b110001 ,
b1 -
b110 %
b110 +
b110 2
b110 4
b110011 (
b110011 )
1&
10
b1010 '
b1010 *
b1010 /
b110011 3
1!
#531000
b110100 "
b110100 1
#535000
0!
#540000
b1000000 .
b110 -
b1110100 ,
b100 %
b100 +
b100 2
b100 4
b110100 3
b1 '
b1 *
b1 /
b110100 (
b110100 )
1!
#541000
b110101 "
b110101 1
#545000
0!
#550000
b100 .
b110001 ,
b10 -
b111 %
b111 +
b111 2
b111 4
b110101 (
b110101 )
b100 '
b100 *
b100 /
b110101 3
1!
#551000
b110110 "
b110110 1
#555000
0!
#560000
b100000 .
b101 -
b10110 ,
b10 %
b10 +
b10 2
b10 4
b110110 3
b1 '
b1 *
b1 /
b110110 (
b110110 )
1!
#561000
b110111 "
b110111 1
#565000
0!
#570000
b10000 .
b100111 ,
b100 -
b1 %
b1 +
b1 2
b1 4
b110111 (
b110111 )
b110 '
b110 *
b110 /
b110111 3
1!
#571000
b111000 "
b111000 1
#575000
0!
#580000
b10 .
b1 -
b111010 ,
b110 %
b110 +
b110 2
b110 4
b111000 3
b111 '
b111 *
b111 /
b111000 (
b111000 )
1!
#581000
b111001 "
b111001 1
#585000
0!
#590000
b1000 .
b110001 ,
b11 -
b101 %
b101 +
b101 2
b101 4
b111001 (
b111001 )
b1010 '
b1010 *
b1010 /
b111001 3
1!
#591000
b111010 "
b111010 1
#595000
0!
#600000
b1 .
1$
b0 -
b111010 ,
b0 %
b0 +
b0 2
b0 4
b111010 3
b1 '
b1 *
b1 /
b111010 (
b111010 )
1!
#601000
b111011 "
b111011 1
#605000
0!
#610000
0$
b111010 ,
b11 %
b11 +
b11 2
b11 4
b111011 (
b111011 )
0&
00
b1010 '
b1010 *
b1010 /
b111011 3
1!
#611000
b111100 "
b111100 1
#615000
0!
#620000
b10000 .
b100 -
b101100 ,
b1 %
b1 +
b1 2
b1 4
b111100 3
1&
10
b111100 (
b111100 )
1!
#621000
b111101 "
b111101 1
#625000
0!
#630000
b100000 .
b11101 ,
b101 -
b10 %
b10 +
b10 2
b10 4
b111101 (
b111101 )
b1100 '
b1100 *
b1100 /
b111101 3
1!
#631000
b111110 "
b111110 1
#635000
0!
#640000
b100 .
b10 -
b111010 ,
b111 %
b111 +
b111 2
b111 4
b111110 3
b1101 '
b1101 *
b1101 /
b111110 (
b111110 )
1!
#641000
b111111 "
b111111 1
#645000
0!
#650000
b1000000 .
b1111111 ,
b110 -
b100 %
b100 +
b100 2
b100 4
b111111 (
b111111 )
b1010 '
b1010 *
b1010 /
b111111 3
1!
#651000
b1000000 "
b1000000 1
#655000
0!
#660000
b0 ,
b1000000 3
b1111 '
b1111 *
b1111 /
b1000000 (
b1000000 )
1!
#661000
b1000001 "
b1000001 1
#665000
0!
#670000
b100 .
b1000101 ,
b10 -
b111 %
b111 +
b111 2
b111 4
b1000001 (
b1000001 )
b0 '
b0 *
b0 /
b1000001 3
1!
#671000
b1000010 "
b1000010 1
#675000
0!
#680000
b100000 .
b101 -
b1100010 ,
b10 %
b10 +
b10 2
b10 4
b1000010 3
b101 '
b101 *
b101 /
b1000010 (
b1000010 )
1!
#681000
b1000011 "
b1000011 1
#685000
0!
#690000
b10000 .
b1010011 ,
b100 -
b1 %
b1 +
b1 2
b1 4
b1000011 (
b1000011 )
b10 '
b10 *
b10 /
b1000011 3
1!
#691000
b1000100 "
b1000100 1
#695000
0!
#700000
b1 .
b0 -
b1000101 ,
b11 %
b11 +
b11 2
b11 4
b1000100 3
b11 '
b11 *
b11 /
b1000100 (
b1000100 )
1!
#701000
b1000101 "
b1000101 1
#705000
0!
#710000
1$
b0 %
b0 +
b0 2
b0 4
b1000101 (
b1000101 )
b101 '
b101 *
b101 /
b1000101 3
1!
#711000
b1000110 "
b1000110 1
#715000
0!
#720000
b1000 .
0$
b11 -
b101 %
b101 +
b101 2
b101 4
b1001110 ,
b1000110 3
0&
00
b1000110 (
b1000110 )
1!
#721000
b1000111 "
b1000111 1
#725000
0!
#730000
b10 .
b1000101 ,
b1 -
b110 %
b110 +
b110 2
b110 4
b1000111 (
b1000111 )
1&
10
b1110 '
b1110 *
b1110 /
b1000111 3
1!
#731000
b1001000 "
b1001000 1
#735000
0!
#740000
b10000 .
b100 -
b1011000 ,
b1 %
b1 +
b1 2
b1 4
b1001000 3
b101 '
b101 *
b101 /
b1001000 (
b1001000 )
1!
#741000
b1001001 "
b1001001 1
#745000
0!
#750000
b100000 .
b1101001 ,
b101 -
b10 %
b10 +
b10 2
b10 4
b1001001 (
b1001001 )
b1000 '
b1000 *
b1000 /
b1001001 3
1!
#751000
b1001010 "
b1001010 1
#755000
0!
#760000
b100 .
b10 -
b1001110 ,
b111 %
b111 +
b111 2
b111 4
b1001010 3
b1001 '
b1001 *
b1001 /
b1001010 (
b1001010 )
1!
#761000
b1001011 "
b1001011 1
#765000
0!
#770000
b1000000 .
b1011 ,
b110 -
b100 %
b100 +
b100 2
b100 4
b1001011 (
b1001011 )
b1110 '
b1110 *
b1110 /
b1001011 3
1!
#771000
b1001100 "
b1001100 1
#775000
0!
#780000
b10 .
b1 -
b1001110 ,
b110 %
b110 +
b110 2
b110 4
b1001100 3
b1011 '
b1011 *
b1011 /
b1001100 (
b1001100 )
1!
#781000
b1001101 "
b1001101 1
#785000
0!
#790000
b1000 .
b1000101 ,
b11 -
b101 %
b101 +
b101 2
b101 4
b1001101 (
b1001101 )
b1110 '
b1110 *
b1110 /
b1001101 3
1!
#791000
b1001110 "
b1001110 1
#795000
0!
#800000
b1 .
1$
b0 -
b1001110 ,
b0 %
b0 +
b0 2
b0 4
b1001110 3
b101 '
b101 *
b101 /
b1001110 (
b1001110 )
1!
#801000
b1001111 "
b1001111 1
#805000
0!
#810000
0$
b1001110 ,
b11 %
b11 +
b11 2
b11 4
b1001111 (
b1001111 )
0&
00
b1110 '
b1110 *
b1110 /
b1001111 3
1!
#811000
b1010000 "
b1010000 1
#815000
0!
#820000
b1000 .
b11 -
b1011000 ,
b101 %
b101 +
b101 2
b101 4
b1010000 3
1&
10
b1010000 (
b1010000 )
1!
#821000
b1010001 "
b1010001 1
#825000
0!
#830000
b10 .
b1010011 ,
b1 -
b110 %
b110 +
b110 2
b110 4
b1010001 (
b1010001 )
b1000 '
b1000 *
b1000 /
b1010001 3
1!
#831000
b1010010 "
b1010010 1
#835000
0!
#840000
b1 .
b0 -
b1010011 ,
b11 %
b11 +
b11 2
b11 4
b1010010 3
b11 '
b11 *
b11 /
b1010010 (
b1010010 )
1!
#841000
b1010011 "
b1010011 1
#845000
0!
#850000
1$
b0 %
b0 +
b0 2
b0 4
b1010011 (
b1010011 )
b1010011 3
1!
#851000
b1010100 "
b1010100 1
#855000
0!
#860000
b100000 .
0$
b101 -
b10 %
b10 +
b10 2
b10 4
b1110100 ,
b1010100 3
0&
00
b1010100 (
b1010100 )
1!
#861000
b1010101 "
b1010101 1
#865000
0!
#870000
b10000 .
b1000101 ,
b100 -
b1 %
b1 +
b1 2
b1 4
b1010101 (
b1010101 )
1&
10
b100 '
b100 *
b100 /
b1010101 3
1!
#871000
b1010110 "
b1010110 1
#875000
0!
#880000
b1000000 .
b110 -
b10110 ,
b100 %
b100 +
b100 2
b100 4
b1010110 3
b101 '
b101 *
b101 /
b1010110 (
b1010110 )
1!
#881000
b1010111 "
b1010111 1
#885000
0!
#890000
b100 .
b1010011 ,
b10 -
b111 %
b111 +
b111 2
b111 4
b1010111 (
b1010111 )
b110 '
b110 *
b110 /
b1010111 3
1!
#891000
b1011000 "
b1011000 1
#895000
0!
#900000
b1 .
1$
b0 -
b1011000 ,
b0 %
b0 +
b0 2
b0 4
b1011000 3
b11 '
b11 *
b11 /
b1011000 (
b1011000 )
1!
#901000
b1011001 "
b1011001 1
#905000
0!
#910000
0$
b1011000 ,
b11 %
b11 +
b11 2
b11 4
b1011001 (
b1011001 )
0&
00
b1000 '
b1000 *
b1000 /
b1011001 3
1!
#911000
b1011010 "
b1011010 1
#915000
0!
#920000
b10 .
b1 -
b1011000 ,
b110 %
b110 +
b110 2
b110 4
b1011010 3
1&
10
b1011010 (
b1011010 )
1!
#921000
b1011011 "
b1011011 1
#925000
0!
#930000
b1000 .
b1010011 ,
b11 -
b101 %
b101 +
b101 2
b101 4
b1011011 (
b1011011 )
b1011011 3
1!
#931000
b1011100 "
b1011100 1
#935000
0!
#940000
b100 .
b10 -
b1011000 ,
b111 %
b111 +
b111 2
b111 4
b1011100 3
b11 '
b11 *
b11 /
b1011100 (
b1011100 )
1!
#941000
b1011101 "
b1011101 1
#945000
0!
#950000
b1000000 .
b11101 ,
b110 -
b100 %
b100 +
b100 2
b100 4
b1011101 (
b1011101 )
b1000 '
b1000 *
b1000 /
b1011101 3
1!
#951000
b1011110 "
b1011110 1
#955000
0!
#960000
b10000 .
b100 -
b1001110 ,
b1 %
b1 +
b1 2
b1 4
b1011110 3
b1101 '
b1101 *
b1101 /
b1011110 (
b1011110 )
1!
#961000
b1011111 "
b1011111 1
#965000
0!
#970000
b100000 .
b1111111 ,
b101 -
b10 %
b10 +
b10 2
b10 4
b1011111 (
b1011111 )
b1110 '
b1110 *
b1110 /
b1011111 3
1!
#971000
b1100000 "
b1100000 1
#975000
0!
#980000
b10 .
b1 -
b1100010 ,
b110 %
b110 +
b110 2
b110 4
b1100000 3
b1111 '
b1111 *
b1111 /
b1100000 (
b1100000 )
1!
#981000
b1100001 "
b1100001 1
#985000
0!
#990000
b1000 .
b1101001 ,
b11 -
b101 %
b101 +
b101 2
b101 4
b1100001 (
b1100001 )
b10 '
b10 *
b10 /
b1100001 3
1!
#991000
b1100010 "
b1100010 1
#995000
0!
#1000000
b1 .
1$
b0 -
b1100010 ,
b0 %
b0 +
b0 2
b0 4
b1100010 3
b1001 '
b1001 *
b1001 /
b1100010 (
b1100010 )
1!
#1001000
b1100011 "
b1100011 1
#1005000
0!
#1010000
0$
b1100010 ,
b11 %
b11 +
b11 2
b11 4
b1100011 (
b1100011 )
0&
00
b10 '
b10 *
b10 /
b1100011 3
1!
#1011000
b1100100 "
b1100100 1
#1015000
0!
#1020000
b10000 .
b100 -
b1110100 ,
b1 %
b1 +
b1 2
b1 4
b1100100 3
1&
10
b1100100 (
b1100100 )
1!
#1021000
b1100101 "
b1100101 1
#1025000
0!
#1030000
b100000 .
b1000101 ,
b101 -
b10 %
b10 +
b10 2
b10 4
b1100101 (
b1100101 )
b100 '
b100 *
b100 /
b1100101 3
1!
#1031000
b1100110 "
b1100110 1
#1035000
0!
#1040000
b100 .
b10 -
b1100010 ,
b111 %
b111 +
b111 2
b111 4
b1100110 3
b101 '
b101 *
b101 /
b1100110 (
b1100110 )
1!
#1041000
b1100111 "
b1100111 1
#1045000
0!
#1050000
b1000000 .
b100111 ,
b110 -
b100 %
b100 +
b100 2
b100 4
b1100111 (
b1100111 )
b10 '
b10 *
b10 /
b1100111 3
1!
#1051000
b1101000 "
b1101000 1
#1055000
0!
#1060000
b1 .
b0 -
b1101001 ,
b11 %
b11 +
b11 2
b11 4
b1101000 3
b111 '
b111 *
b111 /
b1101000 (
b1101000 )
1!
#1061000
b1101001 "
b1101001 1
#1065000
0!
#1070000
1$
b0 %
b0 +
b0 2
b0 4
b1101001 (
b1101001 )
b1001 '
b1001 *
b1001 /
b1101001 3
1!
#1071000
b1101010 "
b1101010 1
#1075000
0!
#1080000
b1000 .
0$
b11 -
b101 %
b101 +
b101 2
b101 4
b1100010 ,
b1101010 3
0&
00
b1101010 (
b1101010 )
1!
#1081000
b1101011 "
b1101011 1
#1085000
0!
#1090000
b10 .
b1101001 ,
b1 -
b110 %
b110 +
b110 2
b110 4
b1101011 (
b1101011 )
1&
10
b10 '
b10 *
b10 /
b1101011 3
1!
#1091000
b1101100 "
b1101100 1
#1095000
0!
#1100000
b1000000 .
b110 -
b101100 ,
b100 %
b100 +
b100 2
b100 4
b1101100 3
b1001 '
b1001 *
b1001 /
b1101100 (
b1101100 )
1!
#1101000
b1101101 "
b1101101 1
#1105000
0!
#1110000
b100 .
b1101001 ,
b10 -
b111 %
b111 +
b111 2
b111 4
b1101101 (
b1101101 )
b1100 '
b1100 *
b1100 /
b1101101 3
1!
#1111000
b1101110 "
b1101110 1
#1115000
0!
#1120000
b100000 .
b101 -
b1001110 ,
b10 %
b10 +
b10 2
b10 4
b1101110 3
b1001 '
b1001 *
b1001 /
b1101110 (
b1101110 )
1!
#1121000
b1101111 "
b1101111 1
#1125000
0!
#1130000
b10000 .
b1111111 ,
b100 -
b1 %
b1 +
b1 2
b1 4
b1101111 (
b1101111 )
b1110 '
b1110 *
b1110 /
b1101111 3
1!
#1131000
b1110000 "
b1110000 1
#1135000
0!
#1140000
b100 .
b10 -
b1110100 ,
b111 %
b111 +
b111 2
b111 4
b1110000 3
b1111 '
b1111 *
b1111 /
b1110000 (
b1110000 )
1!
#1141000
b1110001 "
b1110001 1
#1145000
0!
#1150000
b1000000 .
b110001 ,
b110 -
b100 %
b100 +
b100 2
b100 4
b1110001 (
b1110001 )
b100 '
b100 *
b100 /
b1110001 3
1!
#1151000
b1110010 "
b1110010 1
#1155000
0!
#1160000
b10000 .
b100 -
b1100010 ,
b1 %
b1 +
b1 2
b1 4
b1110010 3
b1 '
b1 *
b1 /
b1110010 (
b1110010 )
1!
#1161000
b1110011 "
b1110011 1
#1165000
0!
#1170000
b100000 .
b1010011 ,
b101 -
b10 %
b10 +
b10 2
b10 4
b1110011 (
b1110011 )
b10 '
b10 *
b10 /
b1110011 3
1!
#1171000
b1110100 "
b1110100 1
#1175000
0!
#1180000
b1 .
1$
b0 -
b1110100 ,
b0 %
b0 +
b0 2
b0 4
b1110100 3
b11 '
b11 *
b11 /
b1110100 (
b1110100 )
1!
#1181000
b1110101 "
b1110101 1
#1185000
0!
#1190000
0$
b1110100 ,
b11 %
b11 +
b11 2
b11 4
b1110101 (
b1110101 )
0&
00
b100 '
b100 *
b100 /
b1110101 3
1!
#1191000
b1110110 "
b1110110 1
#1195000
0!
#1200000
b10 .
b1 -
b1110100 ,
b110 %
b110 +
b110 2
b110 4
b1110110 3
1&
10
b1110110 (
b1110110 )
1!
#1201000
b1110111 "
b1110111 1
#1205000
0!
#1210000
b1000 .
b1111111 ,
b11 -
b101 %
b101 +
b101 2
b101 4
b1110111 (
b1110111 )
b1110111 3
1!
#1211000
b1111000 "
b1111000 1
#1215000
0!
