Unidad 3 - Codigos de Control de Errores/unidad3_rtl/unidad3/hamming_7_4_decoder/error_corrector.sv
module error_corrector (
    output logic [4-1:0] o_info,
    output logic         o_is_corrected,
    input  logic         i_zero_syndrome,
    input  logic [3-1:0] i_syndrome,
    input  logic [7-1:0] i_message,
    input  logic         i_clk,
    input  logic         i_rst
);

/*
    | 1 0 1 1 1 0 0 |
H = | 1 1 1 0 0 1 0 |
    | 0 1 1 1 0 0 1 |

h0 = 110 -> 3'b011
h1 = 011 -> 3'b110
h2 = 111 -> 3'b111
h3 = 101 -> 3'b101
h4 = 100 -> 3'b001
h5 = 010 -> 3'b010
h6 = 001 -> 3'b100

r = v + e
v + e + e = v
r + e = v
*/

logic [3-1:0] error_position;
logic [7-1:0] estimated_error; // e
logic [7-1:0] corrected_message;
logic [4-1:0] info_d;
logic         is_corrected_d;

always_comb begin
    case (i_syndrome)
        3'b011:  error_position = 3'd0; //h0
        3'b110:  error_position = 3'd1; //h1
        3'b111:  error_position = 3'd2; //h2
        3'b101:  error_position = 3'd3; //h3
        3'b001:  error_position = 3'd4; //h4
        3'b010:  error_position = 3'd5; //h5
        3'b100:  error_position = 3'd6; //h6
        default: error_position = 3'd0;
    endcase
end

always_comb begin
    estimated_error                 = 7'd0;
    estimated_error[error_position] = 1'b1;
end

assign corrected_message = (i_zero_syndrome) ? i_message : (i_message ^ estimated_error);

always_ff @(posedge i_clk) begin
    if(i_rst) begin
        info_d         <= 4'd0;
        is_corrected_d <= 1'b0;
    end
    else begin
        info_d         <= corrected_message[3:0];
        is_corrected_d <= !i_zero_syndrome;
    end
end

assign o_info         = info_d;
assign o_is_corrected = is_corrected_d;

endmodule

Unidad 3 - Codigos de Control de Errores/unidad3_rtl/unidad3/hamming_7_4_decoder/syndrome_calculator.sv
module syndrome_calculator (
    output logic [3-1:0] o_syndrome,
    output logic         o_zero_syndrome,
    input  logic [7-1:0] i_message,
    input  logic         i_clk,
    input  logic         i_rst
);

/*
    | 1 0 1 1 1 0 0 |
H = | 1 1 1 0 0 1 0 |
    | 0 1 1 1 0 0 1 |

      | 1 1 0 |
      | 0 1 1 |
      | 1 1 1 |
H^T = | 1 0 1 |
      | 1 0 0 |
      | 0 1 0 |
      | 0 0 1 |

s (syndrome) = r (received message) * H^T (transposed H)
r = v + e

s0 = r0 + r2 + r3 + r4
s1 = r0 + r1 + r2 + r5
s2 = r1 + r2 + r3 + r6
*/

logic [7-1:0] message_d;
logic [3-1:0] syndrome;

always_ff @(posedge i_clk) begin
    if(i_rst) begin
        message_d <= 7'd0;
    end
    else begin
        message_d <= i_message;
    end
end

always_comb begin
    syndrome[0] = message_d[0] ^ message_d[2] ^ message_d[3] ^ message_d[4];
    syndrome[1] = message_d[0] ^ message_d[1] ^ message_d[2] ^ message_d[5];
    syndrome[2] = message_d[1] ^ message_d[2] ^ message_d[3] ^ message_d[6];
end

assign o_syndrome      = syndrome;
assign o_zero_syndrome = (|syndrome == 1'b0);

// |syndrome = syndrome[0] | syndrome[1] | syndrome[2]

endmodule

Unidad 3 - Codigos de Control de Errores/unidad3_rtl/unidad3/hamming_7_4_decoder/hamming_decoder.sv
module hamming_decoder (
    output logic [4-1:0] o_info,
    output logic         o_is_corrected,
    input  logic [7-1:0] i_message,
    input  logic         i_clk,
    input  logic         i_rst
);

logic [7-1:0] message_d;
logic [3-1:0] syndrome;
logic         zero_syndrome;

always_ff @(posedge i_clk) begin
    message_d <= i_message;
end

syndrome_calculator u_syndrome_calculator(
    .o_syndrome      (syndrome),
    .o_zero_syndrome (zero_syndrome),
    .i_message       (i_message),
    .i_clk           (i_clk),
    .i_rst           (i_rst)
);

error_corrector u_error_corrector(
    .o_info          (o_info),
    .o_is_corrected  (o_is_corrected),
    .i_zero_syndrome (zero_syndrome),
    .i_syndrome      (syndrome),
    .i_message       (message_d),
    .i_clk           (i_clk),
    .i_rst           (i_rst)
);
    
endmodule

Unidad 3 - Codigos de Control de Errores/unidad3_rtl/unidad3/hamming_7_4_encoder/hamming_encoder.sv
module hamming_encoder (
    output logic [7-1:0] o_message,
    input  logic [4-1:0] i_info
);

/*
    | 1 0 0 0 1 1 0 |
G = | 0 1 0 0 0 1 1 |
    | 0 0 1 0 1 1 1 |
    | 0 0 0 1 1 0 1 |

v (message) = u (info) * G (generator matrix)
p = [p0 p1 p2]
    LSB       MSB
u = [u0 u1 u2 u3]
v = [u0 u1 u2 u3 - p0 p1 p2]
p0 = u0 + u2 + u3
p1 = u0 + u1 + u2
p2 = u1 + u2 + u3
*/

logic [3-1:0] parity;
logic [7-1:0] message;

assign message[0] = i_info[0];
assign message[1] = i_info[1];
assign message[2] = i_info[2];
assign message[3] = i_info[3];

assign parity[0] = i_info[0] ^ i_info[2] ^ i_info[3];
assign parity[1] = i_info[0] ^ i_info[1] ^ i_info[2];
assign parity[2] = i_info[1] ^ i_info[2] ^ i_info[3];

assign message[4] = parity[0];
assign message[5] = parity[1];
assign message[6] = parity[2];

assign o_message = message;

endmodule

Unidad 3 - Codigos de Control de Errores/unidad3_rtl/unidad3/hamming_7_4/hamming_7_4.sv
module hamming_7_4 (
    output logic [4-1:0] o_info,
    output logic         o_is_corrected,
    input  logic [4-1:0] i_info,
    input  logic [7-1:0] i_error_vector,
    input  logic         i_clk,
    input  logic         i_rst
);

/*
i_info ---------> [reg] ---> encoder ---> (+) ---> decoder ---> o_info
                                               ^
                                               |
    i_error_vector -> [reg] --------------------

    el vector de error se registra junto con la informacion, asi la suma
    queda alineada en latencia
*/

logic [4-1:0] info_d;
logic [7-1:0] error_vector_d;
logic [7-1:0] message;
logic [7-1:0] received;

always_ff @(posedge i_clk) begin
    if(i_rst) begin
        info_d         <= 'd0;
        error_vector_d <= 'd0;
    end
    else begin
        info_d         <= i_info;
        error_vector_d <= i_error_vector;
    end
end

hamming_encoder u_hamming_encoder(
    .o_message(message),
    .i_info(info_d)
);

assign received = message ^ error_vector_d;

hamming_decoder u_hamming_decoder(
    .o_info(o_info),
    .o_is_corrected(o_is_corrected),
    .i_message(received),
    .i_clk(i_clk),
    .i_rst(i_rst)
);

endmodule

Unidad 3 - Codigos de Control de Errores/unidad3_rtl/unidad3/hamming_7_4/hamming_7_4.vcd
$date
	Tue Aug 11 02:20:50 2026
$end
$version
	Icarus Verilog
$end
$timescale
	1ps
$end
$scope module hamming_7_4 $end
$var wire 1 ! i_clk $end
$var wire 7 " i_error_vector [6:0] $end
$var wire 4 # i_info [3:0] $end
$var wire 1 $ i_rst $end
$var wire 7 % received [6:0] $end
$var wire 1 & o_is_corrected $end
$var wire 4 ' o_info [3:0] $end
$var wire 7 ( message [6:0] $end
$var reg 7 ) error_vector_d [6:0] $end
$var reg 4 * info_d [3:0] $end
$scope module u_hamming_decoder $end
$var wire 1 ! i_clk $end
$var wire 7 + i_message [6:0] $end
$var wire 1 $ i_rst $end
$var wire 1 , zero_syndrome $end
$var wire 3 - syndrome [2:0] $end
$var wire 1 & o_is_corrected $end
$var wire 4 . o_info [3:0] $end
$var reg 7 / message_d [6:0] $end
$scope module u_error_corrector $end
$var wire 1 ! i_clk $end
$var wire 7 0 i_message [6:0] $end
$var wire 1 $ i_rst $end
$var wire 4 1 o_info [3:0] $end
$var wire 1 & o_is_corrected $end
$var wire 1 , i_zero_syndrome $end
$var wire 3 2 i_syndrome [2:0] $end
$var wire 7 3 corrected_message [6:0] $end
$var reg 3 4 error_position [2:0] $end
$var reg 7 5 estimated_error [6:0] $end
$var reg 4 6 info_d [3:0] $end
$var reg 1 7 is_corrected_d $end
$upscope $end
$scope module u_syndrome_calculator $end
$var wire 1 ! i_clk $end
$var wire 7 8 i_message [6:0] $end
$var wire 1 $ i_rst $end
$var wire 3 9 o_syndrome [2:0] $end
$var wire 1 , o_zero_syndrome $end
$var reg 7 : message_d [6:0] $end
$var reg 3 ; syndrome [2:0] $end
$upscope $end
$upscope $end
$scope module u_hamming_encoder $end
$var wire 4 < i_info [3:0] $end
$var wire 7 = o_message [6:0] $end
$var wire 3 > parity [2:0] $end
$var wire 7 ? message [6:0] $end
$upscope $end
$upscope $end
$enddefinitions $end
$comment Show the parameter values. $end
$dumpall
$end
#0
$dumpvars
b0 ?
b0 >
b0 =
b0 <
b0 ;
b0 :
b0 9
b0 8
07
b0 6
b1 5
b0 4
bx 3
b0 2
b0 1
bx 0
bx /
b0 .
b0 -
1,
b0 +
b0 *
b0 )
b0 (
b0 '
0&
b0 %
1$
b0 #
b0 "
1!
$end
#5000
0!
#10000
0$
b0 3
b0 /
b0 0
1!
#15000
0!
#20000
1!
#21000
b1 "
#25000
0!
#30000
b1 %
b1 +
b1 8
b1 )
1!
#31000
b10 "
#35000
0!
#40000
0,
b11 -
b11 2
b11 9
b11 ;
b0 3
b10 %
b10 +
b10 8
b1 :
b1 /
b1 0
b10 )
1!
#41000
b11 "
#45000
0!
#50000
b10 5
b0 3
b1 4
b11 %
b11 +
b11 8
b110 -
b110 2
b110 9
b110 ;
b11 )
b10 /
b10 0
1&
17
b10 :
1!
#51000
b100 "
#55000
0!
#60000
b1000 5
b11 4
b1011 3
b101 -
b101 2
b101 9
b101 ;
b100 %
b100 +
b100 8
b11 :
b11 /
b11 0
b100 )
1!
#61000
b101 "
#65000
0!
#70000
b100 5
b0 3
b10 4
b101 %
b101 +
b101 8
b111 -
b111 2
b111 9
b111 ;
b101 )
b100 /
b100 0
b1011 '
b1011 .
b1011 1
b1011 6
b100 :
1!
#71000
b110 "
#75000
0!
#80000
b1000000 5
b110 4
b1000101 3
b100 -
b100 2
b100 9
b100 ;
b110 %
b110 +
b110 8
b101 :
b0 '
b0 .
b0 1
b0 6
b101 /
b101 0
b110 )
1!
#81000
b111 "
#85000
0!
#90000
b10000 5
b10110 3
b100 4
b111 %
b111 +
b111 8
b1 -
b1 2
b1 9
b1 ;
b111 )
b110 /
b110 0
b101 '
b101 .
b101 1
b101 6
b110 :
1!
#91000
b1000 "
#95000
0!
#100000
b100000 5
b101 4
b100111 3
b10 -
b10 2
b10 9
b10 ;
b1000 %
b1000 +
b1000 8
b111 :
b110 '
b110 .
b110 1
b110 6
b111 /
b111 0
b1000 )
1!
#101000
b1001 "
#105000
0!
#110000
b1000 5
b0 3
b11 4
b1001 %
b1001 +
b1001 8
b101 -
b101 2
b101 9
b101 ;
b1001 )
b1000 /
b1000 0
b111 '
b111 .
b111 1
b111 6
b1000 :
1!
#111000
b1010 "
#115000
0!
#120000
b10 5
b1 4
b1011 3
b110 -
b110 2
b110 9
b110 ;
b1010 %
b1010 +
b1010 8
b1001 :
b0 '
b0 .
b0 1
b0 6
b1001 /
b1001 0
b1010 )
1!
#121000
b1011 "
#125000
0!
#130000
b1 5
b1011 3
b0 4
b1011 %
b1011 +
b1011 8
b11 -
b11 2
b11 9
b11 ;
b1011 )
b1010 /
b1010 0
b1011 '
b1011 .
b1011 1
b1011 6
b1010 :
1!
#131000
b1100 "
#135000
0!
#140000
1,
b1011 3
b0 -
b0 2
b0 9
b0 ;
b1100 %
b1100 +
b1100 8
b1011 :
b1011 /
b1011 0
b1100 )
1!
#141000
b1101 "
#145000
0!
#150000
b100000 5
0,
b101 4
b1101 %
b1101 +
b1101 8
b101100 3
b10 -
b10 2
b10 9
b10 ;
b1101 )
b1100 /
b1100 0
0&
07
b1100 :
1!
#151000
b1110 "
#155000
0!
#160000
b10000 5
b100 4
b11101 3
b1 -
b1 2
b1 9
b1 ;
b1110 %
b1110 +
b1110 8
b1101 :
1&
17
b1100 '
b1100 .
b1100 1
b1100 6
b1101 /
b1101 0
b1110 )
1!
#161000
b1111 "
#165000
0!
#170000
b1000000 5
b1001110 3
b110 4
b1111 %
b1111 +
b1111 8
b100 -
b100 2
b100 9
b100 ;
b1111 )
b1110 /
b1110 0
b1101 '
b1101 .
b1101 1
b1101 6
b1110 :
1!
#171000
b10000 "
#175000
0!
#180000
b100 5
b10 4
b1011 3
b111 -
b111 2
b111 9
b111 ;
b10000 %
b10000 +
b10000 8
b1111 :
b1110 '
b1110 .
b1110 1
b1110 6
b1111 /
b1111 0
b10000 )
1!
#181000
b10001 "
#185000
0!
#190000
b10000 5
b0 3
b100 4
b10001 %
b10001 +
b10001 8
b1 -
b1 2
b1 9
b1 ;
b10001 )
b10000 /
b10000 0
b1011 '
b1011 .
b1011 1
b1011 6
b10000 :
1!
#191000
b10010 "
#195000
0!
#200000
b100000 5
b101 4
b110001 3
b10 -
b10 2
b10 9
b10 ;
b10010 %
b10010 +
b10010 8
b10001 :
b0 '
b0 .
b0 1
b0 6
b10001 /
b10001 0
b10010 )
1!
#201000
b10011 "
#205000
0!
#210000
b100 5
b10110 3
b10 4
b10011 %
b10011 +
b10011 8
b111 -
b111 2
b111 9
b111 ;
b10011 )
b10010 /
b10010 0
b1 '
b1 .
b1 1
b1 6
b10010 :
1!
#211000
b10100 "
#215000
0!
#220000
b1000000 5
b110 4
b1010011 3
b100 -
b100 2
b100 9
b100 ;
b10100 %
b10100 +
b10100 8
b10011 :
b110 '
b110 .
b110 1
b110 6
b10011 /
b10011 0
b10100 )
1!
#221000
b10101 "
#225000
0!
#230000
b10 5
b10110 3
b1 4
b10101 %
b10101 +
b10101 8
b110 -
b110 2
b110 9
b110 ;
b10101 )
b10100 /
b10100 0
b11 '
b11 .
b11 1
b11 6
b10100 :
1!
#231000
b10110 "
#235000
0!
#240000
b1000 5
b11 4
b11101 3
b101 -
b101 2
b101 9
b101 ;
b10110 %
b10110 +
b10110 8
b10101 :
b110 '
b110 .
b110 1
b110 6
b10101 /
b10101 0
b10110 )
1!
#241000
b10111 "
#245000
0!
#250000
b1 5
b10110 3
1,
b0 4
b10111 %
b10111 +
b10111 8
b0 -
b0 2
b0 9
b0 ;
b10111 )
b10110 /
b10110 0
b1101 '
b1101 .
b1101 1
b1101 6
b10110 :
1!
#251000
b11000 "
#255000
0!
#260000
0,
b11 -
b11 2
b11 9
b11 ;
b10110 3
b11000 %
b11000 +
b11000 8
b10111 :
0&
07
b110 '
b110 .
b110 1
b110 6
b10111 /
b10111 0
b11000 )
1!
#261000
b11001 "
#265000
0!
#270000
b1000000 5
b1011000 3
b110 4
b11001 %
b11001 +
b11001 8
b100 -
b100 2
b100 9
b100 ;
b11001 )
b11000 /
b11000 0
1&
17
b11000 :
1!
#271000
b11010 "
#275000
0!
#280000
b100 5
b10 4
b11101 3
b111 -
b111 2
b111 9
b111 ;
b11010 %
b11010 +
b11010 8
b11001 :
b1000 '
b1000 .
b1000 1
b1000 6
b11001 /
b11001 0
b11010 )
1!
#281000
b11011 "
#285000
0!
#290000
b100000 5
b111010 3
b101 4
b11011 %
b11011 +
b11011 8
b10 -
b10 2
b10 9
b10 ;
b11011 )
b11010 /
b11010 0
b1101 '
b1101 .
b1101 1
b1101 6
b11010 :
1!
#291000
b11100 "
#295000
0!
#300000
b10000 5
b100 4
b1011 3
b1 -
b1 2
b1 9
b1 ;
b11100 %
b11100 +
b11100 8
b11011 :
b1010 '
b1010 .
b1010 1
b1010 6
b11011 /
b11011 0
b11100 )
1!
#301000
b11101 "
#305000
0!
#310000
b1 5
b11101 3
b0 4
b11101 %
b11101 +
b11101 8
b11 -
b11 2
b11 9
b11 ;
b11101 )
b11100 /
b11100 0
b1011 '
b1011 .
b1011 1
b1011 6
b11100 :
1!
#311000
b11110 "
#315000
0!
#320000
1,
b11101 3
b0 -
b0 2
b0 9
b0 ;
b11110 %
b11110 +
b11110 8
b11101 :
b1101 '
b1101 .
b1101 1
b1101 6
b11101 /
b11101 0
b11110 )
1!
#321000
b11111 "
#325000
0!
#330000
b1000 5
0,
b11 4
b11111 %
b11111 +
b11111 8
b10110 3
b101 -
b101 2
b101 9
b101 ;
b11111 )
b11110 /
b11110 0
0&
07
b11110 :
1!
#331000
b100000 "
#335000
0!
#340000
b10 5
b1 4
b11101 3
b110 -
b110 2
b110 9
b110 ;
b100000 %
b100000 +
b100000 8
b11111 :
1&
17
b110 '
b110 .
b110 1
b110 6
b11111 /
b11111 0
b100000 )
1!
#341000
b100001 "
#345000
0!
#350000
b100000 5
b0 3
b101 4
b100001 %
b100001 +
b100001 8
b10 -
b10 2
b10 9
b10 ;
b100001 )
b100000 /
b100000 0
b1101 '
b1101 .
b1101 1
b1101 6
b100000 :
1!
#351000
b100010 "
#355000
0!
#360000
b10000 5
b100 4
b110001 3
b1 -
b1 2
b1 9
b1 ;
b100010 %
b100010 +
b100010 8
b100001 :
b0 '
b0 .
b0 1
b0 6
b100001 /
b100001 0
b100010 )
1!
#361000
b100011 "
#365000
0!
#370000
b1000000 5
b1100010 3
b110 4
b100011 %
b100011 +
b100011 8
b100 -
b100 2
b100 9
b100 ;
b100011 )
b100010 /
b100010 0
b1 '
b1 .
b1 1
b1 6
b100010 :
1!
#371000
b100100 "
#375000
0!
#380000
b100 5
b10 4
b100111 3
b111 -
b111 2
b111 9
b111 ;
b100100 %
b100100 +
b100100 8
b100011 :
b10 '
b10 .
b10 1
b10 6
b100011 /
b100011 0
b100100 )
1!
#381000
b100101 "
#385000
0!
#390000
b1000 5
b101100 3
b11 4
b100101 %
b100101 +
b100101 8
b101 -
b101 2
b101 9
b101 ;
b100101 )
b100100 /
b100100 0
b111 '
b111 .
b111 1
b111 6
b100100 :
1!
#391000
b100110 "
#395000
0!
#400000
b10 5
b1 4
b100111 3
b110 -
b110 2
b110 9
b110 ;
b100110 %
b100110 +
b100110 8
b100101 :
b1100 '
b1100 .
b1100 1
b1100 6
b100101 /
b100101 0
b100110 )
1!
#401000
b100111 "
#405000
0!
#410000
b1 5
b100111 3
b0 4
b100111 %
b100111 +
b100111 8
b11 -
b11 2
b11 9
b11 ;
b100111 )
b100110 /
b100110 0
b111 '
b111 .
b111 1
b111 6
b100110 :
1!
#411000
b101000 "
#415000
0!
#420000
1,
b100111 3
b0 -
b0 2
b0 9
b0 ;
b101000 %
b101000 +
b101000 8
b100111 :
b100111 /
b100111 0
b101000 )
1!
#421000
b101001 "
#425000
0!
#430000
b100 5
0,
b10 4
b101001 %
b101001 +
b101001 8
b101100 3
b111 -
b111 2
b111 9
b111 ;
b101001 )
b101000 /
b101000 0
0&
07
b101000 :
1!
#431000
b101010 "
#435000
0!
#440000
b1000000 5
b110 4
b1101001 3
b100 -
b100 2
b100 9
b100 ;
b101010 %
b101010 +
b101010 8
b101001 :
1&
17
b1100 '
b1100 .
b1100 1
b1100 6
b101001 /
b101001 0
b101010 )
1!
#441000
b101011 "
#445000
0!
#450000
b10000 5
b111010 3
b100 4
b101011 %
b101011 +
b101011 8
b1 -
b1 2
b1 9
b1 ;
b101011 )
b101010 /
b101010 0
b1001 '
b1001 .
b1001 1
b1001 6
b101010 :
1!
#451000
b101100 "
#455000
0!
#460000
b100000 5
b101 4
b1011 3
b10 -
b10 2
b10 9
b10 ;
b101100 %
b101100 +
b101100 8
b101011 :
b1010 '
b1010 .
b1010 1
b1010 6
b101011 /
b101011 0
b101100 )
1!
#461000
b101101 "
#465000
0!
#470000
b1 5
b101100 3
1,
b0 4
b101101 %
b101101 +
b101101 8
b0 -
b0 2
b0 9
b0 ;
b101101 )
b101100 /
b101100 0
b1011 '
b1011 .
b1011 1
b1011 6
b101100 :
1!
#471000
b101110 "
#475000
0!
#480000
0,
b11 -
b11 2
b11 9
b11 ;
b101100 3
b101110 %
b101110 +
b101110 8
b101101 :
0&
07
b1100 '
b1100 .
b1100 1
b1100 6
b101101 /
b101101 0
b101110 )
1!
#481000
b101111 "
#485000
0!
#490000
b10 5
b101100 3
b1 4
b101111 %
b101111 +
b101111 8
b110 -
b110 2
b110 9
b110 ;
b101111 )
b101110 /
b101110 0
1&
17
b101110 :
1!
#491000
b110000 "
#495000
0!
#500000
b1000 5
b11 4
b100111 3
b101 -
b101 2
b101 9
b101 ;
b110000 %
b110000 +
b110000 8
b101111 :
b101111 /
b101111 0
b110000 )
1!
#501000
b110001 "
#505000
0!
#510000
b1 5
b110001 3
b0 4
b110001 %
b110001 +
b110001 8
b11 -
b11 2
b11 9
b11 ;
b110001 )
b110000 /
b110000 0
b111 '
b111 .
b111 1
b111 6
b110000 :
1!
#511000
b110010 "
#515000
0!
#520000
1,
b110001 3
b0 -
b0 2
b0 9
b0 ;
b110010 %
b110010 +
b110010 8
b110001 :
b1 '
b1 .
b1 1
b1 6
b110001 /
b110001 0
b110010 )
1!
#521000
b110011 "
#525000
0!
#530000
b1000 5
0,
b11 4
b110011 %
b110011 +
b110011 8
b111010 3
b101 -
b101 2
b101 9
b101 ;
b110011 )
b110010 /
b110010 0
0&
07
b110010 :
1!
#531000
b110100 "
#535000
0!
#540000
b10 5
b1 4
b110001 3
b110 -
b110 2
b110 9
b110 ;
b110100 %
b110100 +
b110100 8
b110011 :
1&
17
b1010 '
b1010 .
b1010 1
b1010 6
b110011 /
b110011 0
b110100 )
1!
#541000
b110101 "
#545000
0!
#550000
b1000000 5
b1110100 3
b110 4
b110101 %
b110101 +
b110101 8
b100 -
b100 2
b100 9
b100 ;
b110101 )
b110100 /
b110100 0
b1 '
b1 .
b1 1
b1 6
b110100 :
1!
#551000
b110110 "
#555000
0!
#560000
b100 5
b10 4
b110001 3
b111 -
b111 2
b111 9
b111 ;
b110110 %
b110110 +
b110110 8
b110101 :
b100 '
b100 .
b100 1
b100 6
b110101 /
b110101 0
b110110 )
1!
#561000
b110111 "
#565000
0!
#570000
b100000 5
b10110 3
b101 4
b110111 %
b110111 +
b110111 8
b10 -
b10 2
b10 9
b10 ;
b110111 )
b110110 /
b110110 0
b1 '
b1 .
b1 1
b1 6
b110110 :
1!
#571000
b111000 "
#575000
0!
#580000
b10000 5
b100 4
b100111 3
b1 -
b1 2
b1 9
b1 ;
b111000 %
b111000 +
b111000 8
b110111 :
b110 '
b110 .
b110 1
b110 6
b110111 /
b110111 0
b111000 )
1!
#581000
b111001 "
#585000
0!
#590000
b10 5
b111010 3
b1 4
b111001 %
b111001 +
b111001 8
b110 -
b110 2
b110 9
b110 ;
b111001 )
b111000 /
b111000 0
b111 '
b111 .
b111 1
b111 6
b111000 :
1!
#591000
b111010 "
#595000
0!
#600000
b1000 5
b11 4
b110001 3
b101 -
b101 2
b101 9
b101 ;
b111010 %
b111010 +
b111010 8
b111001 :
b1010 '
b1010 .
b1010 1
b1010 6
b111001 /
b111001 0
b111010 )
1!
#601000
b111011 "
#605000
0!
#610000
b1 5
b111010 3
1,
b0 4
b111011 %
b111011 +
b111011 8
b0 -
b0 2
b0 9
b0 ;
b111011 )
b111010 /
b111010 0
b1 '
b1 .
b1 1
b1 6
b111010 :
1!
#611000
b111100 "
#615000
0!
#620000
0,
b11 -
b11 2
b11 9
b11 ;
b111010 3
b111100 %
b111100 +
b111100 8
b111011 :
0&
07
b1010 '
b1010 .
b1010 1
b1010 6
b111011 /
b111011 0
b111100 )
1!
#621000
b111101 "
#625000
0!
#630000
b10000 5
b101100 3
b100 4
b111101 %
b111101 +
b111101 8
b1 -
b1 2
b1 9
b1 ;
b111101 )
b111100 /
b111100 0
1&
17
b111100 :
1!
#631000
b111110 "
#635000
0!
#640000
b100000 5
b101 4
b11101 3
b10 -
b10 2
b10 9
b10 ;
b111110 %
b111110 +
b111110 8
b111101 :
b1100 '
b1100 .
b1100 1
b1100 6
b111101 /
b111101 0
b111110 )
1!
#641000
b111111 "
#645000
0!
#650000
b100 5
b111010 3
b10 4
b111111 %
b111111 +
b111111 8
b111 -
b111 2
b111 9
b111 ;
b111111 )
b111110 /
b111110 0
b1101 '
b1101 .
b1101 1
b1101 6
b111110 :
1!
#651000
b1000000 "
#655000
0!
#660000
b1000000 5
b110 4
b1111111 3
b100 -
b100 2
b100 9
b100 ;
b1000000 %
b1000000 +
b1000000 8
b111111 :
b1010 '
b1010 .
b1010 1
b1010 6
b111111 /
b111111 0
b1000000 )
1!
#661000
b1000001 "
#665000
0!
#670000
b0 3
b1000001 %
b1000001 +
b1000001 8
b1000001 )
b1000000 /
b1000000 0
b1111 '
b1111 .
b1111 1
b1111 6
b1000000 :
1!
#671000
b1000010 "
#675000
0!
#680000
b100 5
b10 4
b1000101 3
b111 -
b111 2
b111 9
b111 ;
b1000010 %
b1000010 +
b1000010 8
b1000001 :
b0 '
b0 .
b0 1
b0 6
b1000001 /
b1000001 0
b1000010 )
1!
#681000
b1000011 "
#685000
0!
#690000
b100000 5
b1100010 3
b101 4
b1000011 %
b1000011 +
b1000011 8
b10 -
b10 2
b10 9
b10 ;
b1000011 )
b1000010 /
b1000010 0
b101 '
b101 .
b101 1
b101 6
b1000010 :
1!
#691000
b1000100 "
#695000
0!
#700000
b10000 5
b100 4
b1010011 3
b1 -
b1 2
b1 9
b1 ;
b1000100 %
b1000100 +
b1000100 8
b1000011 :
b10 '
b10 .
b10 1
b10 6
b1000011 /
b1000011 0
b1000100 )
1!
#701000
b1000101 "
#705000
0!
#710000
b1 5
b1000101 3
b0 4
b1000101 %
b1000101 +
b1000101 8
b11 -
b11 2
b11 9
b11 ;
b1000101 )
b1000100 /
b1000100 0
b11 '
b11 .
b11 1
b11 6
b1000100 :
1!
#711000
b1000110 "
#715000
0!
#720000
1,
b1000101 3
b0 -
b0 2
b0 9
b0 ;
b1000110 %
b1000110 +
b1000110 8
b1000101 :
b101 '
b101 .
b101 1
b101 6
b1000101 /
b1000101 0
b1000110 )
1!
#721000
b1000111 "
#725000
0!
#730000
b1000 5
0,
b11 4
b1000111 %
b1000111 +
b1000111 8
b1001110 3
b101 -
b101 2
b101 9
b101 ;
b1000111 )
b1000110 /
b1000110 0
0&
07
b1000110 :
1!
#731000
b1001000 "
#735000
0!
#740000
b10 5
b1 4
b1000101 3
b110 -
b110 2
b110 9
b110 ;
b1001000 %
b1001000 +
b1001000 8
b1000111 :
1&
17
b1110 '
b1110 .
b1110 1
b1110 6
b1000111 /
b1000111 0
b1001000 )
1!
#741000
b1001001 "
#745000
0!
#750000
b10000 5
b1011000 3
b100 4
b1001001 %
b1001001 +
b1001001 8
b1 -
b1 2
b1 9
b1 ;
b1001001 )
b1001000 /
b1001000 0
b101 '
b101 .
b101 1
b101 6
b1001000 :
1!
#751000
b1001010 "
#755000
0!
#760000
b100000 5
b101 4
b1101001 3
b10 -
b10 2
b10 9
b10 ;
b1001010 %
b1001010 +
b1001010 8
b1001001 :
b1000 '
b1000 .
b1000 1
b1000 6
b1001001 /
b1001001 0
b1001010 )
1!
#761000
b1001011 "
#765000
0!
#770000
b100 5
b1001110 3
b10 4
b1001011 %
b1001011 +
b1001011 8
b111 -
b111 2
b111 9
b111 ;
b1001011 )
b1001010 /
b1001010 0
b1001 '
b1001 .
b1001 1
b1001 6
b1001010 :
1!
#771000
b1001100 "
#775000
0!
#780000
b1000000 5
b110 4
b1011 3
b100 -
b100 2
b100 9
b100 ;
b1001100 %
b1001100 +
b1001100 8
b1001011 :
b1110 '
b1110 .
b1110 1
b1110 6
b1001011 /
b1001011 0
b1001100 )
1!
#781000
b1001101 "
#785000
0!
#790000
b10 5
b1001110 3
b1 4
b1001101 %
b1001101 +
b1001101 8
b110 -
b110 2
b110 9
b110 ;
b1001101 )
b1001100 /
b1001100 0
b1011 '
b1011 .
b1011 1
b1011 6
b1001100 :
1!
#791000
b1001110 "
#795000
0!
#800000
b1000 5
b11 4
b1000101 3
b101 -
b101 2
b101 9
b101 ;
b1001110 %
b1001110 +
b1001110 8
b1001101 :
b1110 '
b1110 .
b1110 1
b1110 6
b1001101 /
b1001101 0
b1001110 )
1!
#801000
b1001111 "
#805000
0!
#810000
b1 5
b1001110 3
1,
b0 4
b1001111 %
b1001111 +
b1001111 8
b0 -
b0 2
b0 9
b0 ;
b1001111 )
b1001110 /
b1001110 0
b101 '
b101 .
b101 1
b101 6
b1001110 :
1!
#811000
b1010000 "
#815000
0!
#820000
0,
b11 -
b11 2
b11 9
b11 ;
b1001110 3
b1010000 %
b1010000 +
b1010000 8
b1001111 :
0&
07
b1110 '
b1110 .
b1110 1
b1110 6
b1001111 /
b1001111 0
b1010000 )
1!
#821000
b1010001 "
#825000
0!
#830000
b1000 5
b1011000 3
b11 4
b1010001 %
b1010001 +
b1010001 8
b101 -
b101 2
b101 9
b101 ;
b1010001 )
b1010000 /
b1010000 0
1&
17
b1010000 :
1!
#831000
b1010010 "
#835000
0!
#840000
b10 5
b1 4
b1010011 3
b110 -
b110 2
b110 9
b110 ;
b1010010 %
b1010010 +
b1010010 8
b1010001 :
b1000 '
b1000 .
b1000 1
b1000 6
b1010001 /
b1010001 0
b1010010 )
1!
#841000
b1010011 "
#845000
0!
#850000
b1 5
b1010011 3
b0 4
b1010011 %
b1010011 +
b1010011 8
b11 -
b11 2
b11 9
b11 ;
b1010011 )
b1010010 /
b1010010 0
b11 '
b11 .
b11 1
b11 6
b1010010 :
1!
#851000
b1010100 "
#855000
0!
#860000
1,
b1010011 3
b0 -
b0 2
b0 9
b0 ;
b1010100 %
b1010100 +
b1010100 8
b1010011 :
b1010011 /
b1010011 0
b1010100 )
1!
#861000
b1010101 "
#865000
0!
#870000
b100000 5
0,
b101 4
b1010101 %
b1010101 +
b1010101 8
b1110100 3
b10 -
b10 2
b10 9
b10 ;
b1010101 )
b1010100 /
b1010100 0
0&
07
b1010100 :
1!
#871000
b1010110 "
#875000
0!
#880000
b10000 5
b100 4
b1000101 3
b1 -
b1 2
b1 9
b1 ;
b1010110 %
b1010110 +
b1010110 8
b1010101 :
1&
17
b100 '
b100 .
b100 1
b100 6
b1010101 /
b1010101 0
b1010110 )
1!
#881000
b1010111 "
#885000
0!
#890000
b1000000 5
b10110 3
b110 4
b1010111 %
b1010111 +
b1010111 8
b100 -
b100 2
b100 9
b100 ;
b1010111 )
b1010110 /
b1010110 0
b101 '
b101 .
b101 1
b101 6
b1010110 :
1!
#891000
b1011000 "
#895000
0!
